aip/__init__.py
aip/base.py
aip/bodyanalysis.py
aip/easydl.py
aip/face.py
aip/imagecensor.py
aip/imageclassify.py
aip/imageprocess.py
aip/imagesearch.py
aip/kg.py
aip/mt.py
aip/nlp.py
aip/ocr.py
aip/speech.py
baidu_aip-4.16.12.data/scripts/aip_client
baidu_aip-4.16.12.dist-info/LICENSE
baidu_aip-4.16.12.dist-info/METADATA
baidu_aip-4.16.12.dist-info/WHEEL
baidu_aip-4.16.12.dist-info/top_level.txt
baidu_aip-4.16.12.dist-info/RECORD
