Metadata-Version: 2.1
Name: baidu-aip
Version: 4.16.12
Summary: Baidu AIP SDK
Home-page: https://github.com/Baidu-AIP
Author: Baidu
Author-email: aip@baidu.com
License: Apache License
Keywords: baidu,aip,ocr,antiporn,nlp,face,kg,speech
Platform: UNKNOWN
License-File: LICENSE
Requires-Dist: requests
